{
  "version": "2.4.1",
  "summary": {
    "title": "act 2",
    "owner": "local",
    "description": "activity 2",
    "id": 0
  },
  "detail": {
    "contributors": [],
    "diagrams": [
      {
        "id": 0,
        "title": "diagram 1",
        "diagramType": "STRIDE",
        "placeholder": "New STRIDE diagram description",
        "thumbnail": "./public/content/images/thumbnail.stride.jpg",
        "version": "2.4.1",
        "cells": [
          {
            "position": {
              "x": 702,
              "y": 330
            },
            "size": {
              "width": 120,
              "height": 120
            },
            "attrs": {
              "text": {
                "text": "Web Application"
              },
              "body": {
                "stroke": "red",
                "strokeWidth": 2.5,
                "strokeDasharray": null
              }
            },
            "visible": true,
            "shape": "process",
            "zIndex": 2,
            "ports": {
              "groups": {
                "top": {
                  "position": "top",
                  "attrs": {
                    "circle": {
                      "r": 4,
                      "magnet": true,
                      "stroke": "#5F95FF",
                      "strokeWidth": 1,
                      "fill": "#fff",
                      "style": {
                        "visibility": "hidden"
                      }
                    }
                  }
                },
                "right": {
                  "position": "right",
                  "attrs": {
                    "circle": {
                      "r": 4,
                      "magnet": true,
                      "stroke": "#5F95FF",
                      "strokeWidth": 1,
                      "fill": "#fff",
                      "style": {
                        "visibility": "hidden"
                      }
                    }
                  }
                },
                "bottom": {
                  "position": "bottom",
                  "attrs": {
                    "circle": {
                      "r": 4,
                      "magnet": true,
                      "stroke": "#5F95FF",
                      "strokeWidth": 1,
                      "fill": "#fff",
                      "style": {
                        "visibility": "hidden"
                      }
                    }
                  }
                },
                "left": {
                  "position": "left",
                  "attrs": {
                    "circle": {
                      "r": 4,
                      "magnet": true,
                      "stroke": "#5F95FF",
                      "strokeWidth": 1,
                      "fill": "#fff",
                      "style": {
                        "visibility": "hidden"
                      }
                    }
                  }
                }
              },
              "items": [
                {
                  "group": "top",
                  "id": "1cc156f9-c386-448d-9f3b-31d7bd57658e"
                },
                {
                  "group": "right",
                  "id": "84544158-a88b-4124-b665-95f786b45335"
                },
                {
                  "group": "bottom",
                  "id": "8e2b57c5-4c64-444c-91e0-6acb58809600"
                },
                {
                  "group": "left",
                  "id": "14be4f36-16db-455d-9924-e2f0355c5ab7"
                }
              ]
            },
            "id": "9d656cef-ea4d-423b-86ba-58f7c5cb88c0",
            "data": {
              "type": "tm.Process",
              "name": "Web Application",
              "description": "",
              "outOfScope": false,
              "reasonOutOfScope": "",
              "hasOpenThreats": true,
              "handlesCardPayment": false,
              "handlesGoodsOrServices": false,
              "isWebApplication": false,
              "privilegeLevel": "",
              "threats": [
                {
                  "id": "4c6a20bb-bd58-4b55-94f7-e8a10aaabad2",
                  "title": "Spoofing",
                  "status": "Open",
                  "severity": "TBD",
                  "type": "Spoofing",
                  "description": "Spoofing",
                  "mitigation": "Provide remediation for this threat or a reason if status is N/A",
                  "modelType": "STRIDE",
                  "new": false,
                  "number": 1,
                  "score": ""
                }
              ],
              "threatFrequency": {
                "spoofing": 1,
                "tampering": 0,
                "repudiation": 0,
                "informationDisclosure": 0,
                "denialOfService": 0,
                "elevationOfPrivilege": 0
              }
            }
          },
          {
            "shape": "flow",
            "attrs": {
              "line": {
                "stroke": "#333333",
                "targetMarker": {
                  "name": "block"
                },
                "sourceMarker": {
                  "name": ""
                },
                "strokeDasharray": null
              }
            },
            "width": 200,
            "height": 100,
            "zIndex": 10,
            "connector": "smooth",
            "data": {
              "type": "tm.Flow",
              "name": "Insert Query With Feedback Comments",
              "description": "",
              "outOfScope": false,
              "reasonOutOfScope": "",
              "hasOpenThreats": false,
              "isBidirectional": false,
              "isEncrypted": false,
              "isPublicNetwork": false,
              "protocol": "",
              "threats": []
            },
            "labels": [
              "Insert Query With Feedback Comments"
            ],
            "id": "a48d6f23-28bb-4b5d-8eba-230165cba4c5",
            "source": {
              "cell": "9d656cef-ea4d-423b-86ba-58f7c5cb88c0",
              "port": "1cc156f9-c386-448d-9f3b-31d7bd57658e"
            },
            "target": {
              "cell": "c40cd78c-22c9-486d-a1e2-1613d886ed0e",
              "port": "f7c61a5a-2492-47ef-8519-67c69252b6a8"
            },
            "vertices": []
          },
          {
            "shape": "flow",
            "attrs": {
              "line": {
                "stroke": "#333333",
                "targetMarker": {
                  "name": "block"
                },
                "sourceMarker": {
                  "name": ""
                },
                "strokeDasharray": null
              }
            },
            "width": 200,
            "height": 100,
            "zIndex": 10,
            "connector": "smooth",
            "data": {
              "type": "tm.Flow",
              "name": "Success = 1",
              "description": "",
              "outOfScope": false,
              "reasonOutOfScope": "",
              "hasOpenThreats": false,
              "isBidirectional": false,
              "isEncrypted": false,
              "isPublicNetwork": false,
              "protocol": "",
              "threats": []
            },
            "labels": [
              "Success = 1"
            ],
            "id": "c8ed8b4e-d0a1-4b69-951d-fa2c97a49e10",
            "source": {
              "cell": "c40cd78c-22c9-486d-a1e2-1613d886ed0e",
              "port": "f7c61a5a-2492-47ef-8519-67c69252b6a8"
            },
            "target": {
              "cell": "9d656cef-ea4d-423b-86ba-58f7c5cb88c0",
              "port": "8e2b57c5-4c64-444c-91e0-6acb58809600"
            },
            "vertices": []
          },
          {
            "shape": "flow",
            "attrs": {
              "line": {
                "stroke": "#333333",
                "targetMarker": {
                  "name": "block"
                },
                "sourceMarker": {
                  "name": ""
                },
                "strokeDasharray": null
              }
            },
            "width": 200,
            "height": 100,
            "zIndex": 10,
            "connector": "smooth",
            "data": {
              "type": "tm.Flow",
              "name": "User Sends User Credentials",
              "description": "",
              "outOfScope": false,
              "reasonOutOfScope": "",
              "hasOpenThreats": false,
              "isBidirectional": false,
              "isEncrypted": false,
              "isPublicNetwork": false,
              "protocol": "",
              "threats": []
            },
            "labels": [
              "User Sends User Credentials"
            ],
            "id": "340354ec-437e-4eeb-bc15-e8f5dbb70800",
            "source": {
              "cell": "7ecd7216-eb45-4b8a-be34-f535110c853f",
              "port": "8b6284da-25af-445e-a5e0-ac682bb66f65"
            },
            "target": {
              "cell": "9d656cef-ea4d-423b-86ba-58f7c5cb88c0",
              "port": "1cc156f9-c386-448d-9f3b-31d7bd57658e"
            },
            "vertices": []
          },
          {
            "shape": "flow",
            "attrs": {
              "line": {
                "stroke": "#333333",
                "targetMarker": {
                  "name": "block"
                },
                "sourceMarker": {
                  "name": ""
                },
                "strokeDasharray": null
              }
            },
            "width": 200,
            "height": 100,
            "zIndex": 10,
            "connector": "smooth",
            "data": {
              "type": "tm.Flow",
              "name": "User is Authenticated",
              "description": "",
              "outOfScope": false,
              "reasonOutOfScope": "",
              "hasOpenThreats": false,
              "isBidirectional": false,
              "isEncrypted": false,
              "isPublicNetwork": false,
              "protocol": "",
              "threats": []
            },
            "labels": [
              "User is Authenticated"
            ],
            "id": "7147b011-47ab-4f66-aac1-d9a1d11572dd",
            "source": {
              "cell": "9d656cef-ea4d-423b-86ba-58f7c5cb88c0",
              "port": "14be4f36-16db-455d-9924-e2f0355c5ab7"
            },
            "target": {
              "cell": "7ecd7216-eb45-4b8a-be34-f535110c853f",
              "port": "904e9e75-099b-40b8-b594-bd182b11ae83"
            },
            "vertices": [
              {
                "x": 520,
                "y": 350
              }
            ]
          },
          {
            "shape": "flow",
            "attrs": {
              "line": {
                "stroke": "#333333",
                "targetMarker": {
                  "name": "block"
                },
                "sourceMarker": {
                  "name": ""
                },
                "strokeDasharray": null
              }
            },
            "width": 200,
            "height": 100,
            "zIndex": 10,
            "connector": "smooth",
            "data": {
              "type": "tm.Flow",
              "name": "Insert Feedback Comments",
              "description": "",
              "outOfScope": false,
              "reasonOutOfScope": "",
              "hasOpenThreats": false,
              "isBidirectional": false,
              "isEncrypted": false,
              "isPublicNetwork": false,
              "protocol": "",
              "threats": []
            },
            "labels": [
              "Insert Feedback Comments"
            ],
            "id": "41d950ef-42f7-4f73-9b78-b7b92fb8c3da",
            "source": {
              "cell": "7ecd7216-eb45-4b8a-be34-f535110c853f",
              "port": "904e9e75-099b-40b8-b594-bd182b11ae83"
            },
            "target": {
              "cell": "9d656cef-ea4d-423b-86ba-58f7c5cb88c0",
              "port": "14be4f36-16db-455d-9924-e2f0355c5ab7"
            },
            "vertices": [
              {
                "x": 510,
                "y": 420
              }
            ]
          },
          {
            "shape": "flow",
            "attrs": {
              "line": {
                "stroke": "#333333",
                "targetMarker": {
                  "name": "block"
                },
                "sourceMarker": {
                  "name": ""
                },
                "strokeDasharray": null
              }
            },
            "width": 200,
            "height": 100,
            "zIndex": 10,
            "connector": "smooth",
            "data": {
              "type": "tm.Flow",
              "name": "Feedback Comments Saved",
              "description": "",
              "outOfScope": false,
              "reasonOutOfScope": "",
              "hasOpenThreats": false,
              "isBidirectional": false,
              "isEncrypted": false,
              "isPublicNetwork": false,
              "protocol": "",
              "threats": []
            },
            "labels": [
              "Feedback Comments Saved"
            ],
            "id": "4bdf4aba-e216-4882-9b08-6ae0c2338ee8",
            "source": {
              "cell": "9d656cef-ea4d-423b-86ba-58f7c5cb88c0",
              "port": "8e2b57c5-4c64-444c-91e0-6acb58809600"
            },
            "target": {
              "cell": "7ecd7216-eb45-4b8a-be34-f535110c853f",
              "port": "dfed0ca2-16a6-4860-9512-6b45c3cd0773"
            },
            "vertices": []
          },
          {
            "shape": "flow",
            "attrs": {
              "line": {
                "stroke": "#333333",
                "targetMarker": {
                  "name": "block"
                },
                "sourceMarker": {
                  "name": ""
                },
                "strokeDasharray": null
              }
            },
            "width": 200,
            "height": 100,
            "zIndex": 10,
            "connector": "smooth",
            "data": {
              "type": "tm.Flow",
              "name": "Verified",
              "description": "",
              "outOfScope": false,
              "reasonOutOfScope": "",
              "hasOpenThreats": false,
              "isBidirectional": false,
              "isEncrypted": false,
              "isPublicNetwork": false,
              "protocol": "",
              "threats": []
            },
            "labels": [
              "Verified"
            ],
            "id": "efbecf7d-c20b-4790-88fd-859c73d82eb1",
            "source": {
              "cell": "9f2149c9-953a-4212-9cc5-e1d77b6e6ae5",
              "port": "dfed0ca2-16a6-4860-9512-6b45c3cd0773"
            },
            "target": {
              "cell": "9d656cef-ea4d-423b-86ba-58f7c5cb88c0",
              "port": "1cc156f9-c386-448d-9f3b-31d7bd57658e"
            },
            "vertices": [
              {
                "x": 700,
                "y": 240
              }
            ]
          },
          {
            "shape": "flow",
            "attrs": {
              "line": {
                "stroke": "#333333",
                "targetMarker": {
                  "name": "block"
                },
                "sourceMarker": {
                  "name": ""
                },
                "strokeDasharray": null
              }
            },
            "width": 200,
            "height": 100,
            "zIndex": 10,
            "connector": "smooth",
            "data": {
              "type": "tm.Flow",
              "name": "Verifies the Privilege",
              "description": "",
              "outOfScope": false,
              "reasonOutOfScope": "",
              "hasOpenThreats": false,
              "isBidirectional": false,
              "isEncrypted": false,
              "isPublicNetwork": false,
              "protocol": "",
              "threats": []
            },
            "labels": [
              "Verifies the Privilege"
            ],
            "id": "69fabd32-7064-408b-99d8-df735edf151a",
            "source": {
              "cell": "9f2149c9-953a-4212-9cc5-e1d77b6e6ae5",
              "port": "904e9e75-099b-40b8-b594-bd182b11ae83"
            },
            "target": {
              "cell": "be1967c2-2a7c-4b93-b4d0-d320988b880d",
              "port": "14be4f36-16db-455d-9924-e2f0355c5ab7"
            },
            "vertices": [
              {
                "x": 1020,
                "y": 70
              }
            ]
          },
          {
            "shape": "flow",
            "attrs": {
              "line": {
                "stroke": "#333333",
                "targetMarker": {
                  "name": "block"
                },
                "sourceMarker": {
                  "name": ""
                },
                "strokeDasharray": null
              }
            },
            "width": 200,
            "height": 100,
            "zIndex": 10,
            "connector": "smooth",
            "data": {
              "type": "tm.Flow",
              "name": "Verified",
              "description": "",
              "outOfScope": false,
              "reasonOutOfScope": "",
              "hasOpenThreats": false,
              "isBidirectional": false,
              "isEncrypted": false,
              "isPublicNetwork": false,
              "protocol": "",
              "threats": []
            },
            "labels": [
              "Verified"
            ],
            "id": "815892fa-f698-4629-9e1b-5cd6e08b215e",
            "source": {
              "cell": "be1967c2-2a7c-4b93-b4d0-d320988b880d",
              "port": "14be4f36-16db-455d-9924-e2f0355c5ab7"
            },
            "target": {
              "cell": "9f2149c9-953a-4212-9cc5-e1d77b6e6ae5",
              "port": "904e9e75-099b-40b8-b594-bd182b11ae83"
            },
            "vertices": [
              {
                "x": 1020,
                "y": 140
              }
            ]
          },
          {
            "shape": "trust-boundary-curve",
            "width": 200,
            "height": 100,
            "zIndex": 10,
            "connector": "smooth",
            "data": {
              "type": "tm.Boundary",
              "name": "Generic Trust Boundary",
              "description": "",
              "isTrustBoundary": true,
              "hasOpenThreats": false
            },
            "labels": [
              "Generic Trust Boundary"
            ],
            "id": "f8af8a79-3fb1-478a-90df-e6f9640ba739",
            "source": {
              "x": 670,
              "y": 10
            },
            "target": {
              "x": 650,
              "y": 580
            },
            "vertices": [
              {
                "x": 620,
                "y": 250
              },
              {
                "x": 620,
                "y": 490
              }
            ]
          },
          {
            "shape": "flow",
            "attrs": {
              "line": {
                "stroke": "#333333",
                "targetMarker": {
                  "name": "block"
                },
                "sourceMarker": {
                  "name": ""
                },
                "strokeDasharray": null
              }
            },
            "width": 200,
            "height": 100,
            "zIndex": 10,
            "connector": "smooth",
            "data": {
              "type": "tm.Flow",
              "name": "Auth Verification",
              "description": "",
              "outOfScope": false,
              "reasonOutOfScope": "",
              "hasOpenThreats": false,
              "isBidirectional": false,
              "isEncrypted": false,
              "isPublicNetwork": false,
              "protocol": "",
              "threats": []
            },
            "labels": [
              "Auth Verification"
            ],
            "id": "12342fab-46e5-4ec9-a1ee-46aa17b7a426",
            "source": {
              "cell": "9d656cef-ea4d-423b-86ba-58f7c5cb88c0",
              "port": "1cc156f9-c386-448d-9f3b-31d7bd57658e"
            },
            "target": {
              "cell": "9f2149c9-953a-4212-9cc5-e1d77b6e6ae5",
              "port": "dfed0ca2-16a6-4860-9512-6b45c3cd0773"
            },
            "vertices": [
              {
                "x": 810,
                "y": 240
              }
            ]
          },
          {
            "shape": "trust-boundary-curve",
            "width": 200,
            "height": 100,
            "zIndex": 10,
            "connector": "smooth",
            "data": {
              "type": "tm.Boundary",
              "name": "Generic Trust Boundary",
              "description": "",
              "isTrustBoundary": true,
              "hasOpenThreats": false
            },
            "labels": [
              "Generic Trust Boundary"
            ],
            "id": "d2f33673-465e-4dbc-a7b5-7e43e5a71c95",
            "source": {
              "x": 520,
              "y": 200
            },
            "target": {
              "x": 1010,
              "y": 200
            }
          },
          {
            "shape": "trust-boundary-curve",
            "width": 200,
            "height": 100,
            "zIndex": 10,
            "connector": "smooth",
            "data": {
              "type": "tm.Boundary",
              "name": "Generic Trust Boundary",
              "description": "",
              "isTrustBoundary": true,
              "hasOpenThreats": false
            },
            "labels": [
              "Generic Trust Boundary"
            ],
            "id": "47f5e4e2-d1ae-4852-9433-350d3ccee08e",
            "source": {
              "x": 1130,
              "y": 20
            },
            "target": {
              "x": 1120,
              "y": 570
            },
            "vertices": [
              {
                "x": 1090,
                "y": 250
              }
            ]
          },
          {
            "position": {
              "x": 1150,
              "y": 330
            },
            "size": {
              "width": 200,
              "height": 120
            },
            "attrs": {
              "text": {
                "text": "SQL Database"
              },
              "topLine": {
                "stroke": "red",
                "strokeWidth": 2.5,
                "strokeDasharray": null
              },
              "bottomLine": {
                "stroke": "red",
                "strokeWidth": 2.5,
                "strokeDasharray": null
              }
            },
            "visible": true,
            "shape": "store",
            "ports": {
              "groups": {
                "top": {
                  "position": "top",
                  "attrs": {
                    "circle": {
                      "r": 4,
                      "magnet": true,
                      "stroke": "#5F95FF",
                      "strokeWidth": 1,
                      "fill": "#fff",
                      "style": {
                        "visibility": "hidden"
                      }
                    }
                  }
                },
                "right": {
                  "position": "right",
                  "attrs": {
                    "circle": {
                      "r": 4,
                      "magnet": true,
                      "stroke": "#5F95FF",
                      "strokeWidth": 1,
                      "fill": "#fff",
                      "style": {
                        "visibility": "hidden"
                      }
                    }
                  }
                },
                "bottom": {
                  "position": "bottom",
                  "attrs": {
                    "circle": {
                      "r": 4,
                      "magnet": true,
                      "stroke": "#5F95FF",
                      "strokeWidth": 1,
                      "fill": "#fff",
                      "style": {
                        "visibility": "hidden"
                      }
                    }
                  }
                },
                "left": {
                  "position": "left",
                  "attrs": {
                    "circle": {
                      "r": 4,
                      "magnet": true,
                      "stroke": "#5F95FF",
                      "strokeWidth": 1,
                      "fill": "#fff",
                      "style": {
                        "visibility": "hidden"
                      }
                    }
                  }
                }
              },
              "items": [
                {
                  "group": "top",
                  "id": "f2ba47e9-91ef-485a-91cb-25c1a87b9ce0"
                },
                {
                  "group": "right",
                  "id": "c0857221-3337-4b5e-9983-019279c6d22a"
                },
                {
                  "group": "bottom",
                  "id": "dd0bb854-5126-44be-b525-381ce4cc693d"
                },
                {
                  "group": "left",
                  "id": "f7c61a5a-2492-47ef-8519-67c69252b6a8"
                }
              ]
            },
            "id": "c40cd78c-22c9-486d-a1e2-1613d886ed0e",
            "zIndex": 12,
            "data": {
              "type": "tm.Store",
              "name": "SQL Database",
              "description": "",
              "outOfScope": false,
              "reasonOutOfScope": "",
              "hasOpenThreats": true,
              "isALog": false,
              "isEncrypted": false,
              "isSigned": false,
              "storesCredentials": false,
              "storesInventory": false,
              "threats": [
                {
                  "id": "ecfedc2e-3851-4159-840a-804a81d66896",
                  "title": "Tampering",
                  "status": "Open",
                  "severity": "TBD",
                  "type": "Tampering",
                  "description": "Spoofing",
                  "mitigation": "Provide remediation for this threat or a reason if status is N/A",
                  "modelType": "STRIDE",
                  "new": false,
                  "number": 2,
                  "score": ""
                }
              ],
              "threatFrequency": {
                "tampering": 1,
                "repudiation": 0,
                "informationDisclosure": 0,
                "denialOfService": 0
              }
            }
          },
          {
            "position": {
              "x": 190,
              "y": 330
            },
            "size": {
              "width": 130,
              "height": 120
            },
            "attrs": {
              "text": {
                "text": "Browser Client"
              },
              "body": {
                "stroke": "red",
                "strokeWidth": 2.5,
                "strokeDasharray": null
              }
            },
            "visible": true,
            "shape": "actor",
            "ports": {
              "groups": {
                "top": {
                  "position": "top",
                  "attrs": {
                    "circle": {
                      "r": 4,
                      "magnet": true,
                      "stroke": "#5F95FF",
                      "strokeWidth": 1,
                      "fill": "#fff",
                      "style": {
                        "visibility": "hidden"
                      }
                    }
                  }
                },
                "right": {
                  "position": "right",
                  "attrs": {
                    "circle": {
                      "r": 4,
                      "magnet": true,
                      "stroke": "#5F95FF",
                      "strokeWidth": 1,
                      "fill": "#fff",
                      "style": {
                        "visibility": "hidden"
                      }
                    }
                  }
                },
                "bottom": {
                  "position": "bottom",
                  "attrs": {
                    "circle": {
                      "r": 4,
                      "magnet": true,
                      "stroke": "#5F95FF",
                      "strokeWidth": 1,
                      "fill": "#fff",
                      "style": {
                        "visibility": "hidden"
                      }
                    }
                  }
                },
                "left": {
                  "position": "left",
                  "attrs": {
                    "circle": {
                      "r": 4,
                      "magnet": true,
                      "stroke": "#5F95FF",
                      "strokeWidth": 1,
                      "fill": "#fff",
                      "style": {
                        "visibility": "hidden"
                      }
                    }
                  }
                }
              },
              "items": [
                {
                  "group": "top",
                  "id": "8b6284da-25af-445e-a5e0-ac682bb66f65"
                },
                {
                  "group": "right",
                  "id": "904e9e75-099b-40b8-b594-bd182b11ae83"
                },
                {
                  "group": "bottom",
                  "id": "dfed0ca2-16a6-4860-9512-6b45c3cd0773"
                },
                {
                  "group": "left",
                  "id": "758f3642-fb8d-43d4-9a3c-f2d1448301d6"
                }
              ]
            },
            "id": "7ecd7216-eb45-4b8a-be34-f535110c853f",
            "zIndex": 13,
            "data": {
              "type": "tm.Actor",
              "name": "Browser Client",
              "description": "",
              "outOfScope": false,
              "reasonOutOfScope": "",
              "hasOpenThreats": true,
              "providesAuthentication": false,
              "threats": [
                {
                  "id": "609671e9-99f2-427f-af8f-a3aa18626c1e",
                  "title": "Spoofing",
                  "status": "Open",
                  "severity": "TBD",
                  "type": "Spoofing",
                  "description": "Spoofing",
                  "mitigation": "Provide remediation for this threat or a reason if status is N/A",
                  "modelType": "STRIDE",
                  "new": false,
                  "number": 4,
                  "score": ""
                }
              ],
              "threatFrequency": {
                "spoofing": 1,
                "repudiation": 0
              }
            }
          },
          {
            "position": {
              "x": 682,
              "y": 40
            },
            "size": {
              "width": 160,
              "height": 120
            },
            "attrs": {
              "text": {
                "text": "Authorization Provider"
              },
              "body": {
                "stroke": "red",
                "strokeWidth": 2.5,
                "strokeDasharray": null
              }
            },
            "visible": true,
            "shape": "actor",
            "ports": {
              "groups": {
                "top": {
                  "position": "top",
                  "attrs": {
                    "circle": {
                      "r": 4,
                      "magnet": true,
                      "stroke": "#5F95FF",
                      "strokeWidth": 1,
                      "fill": "#fff",
                      "style": {
                        "visibility": "hidden"
                      }
                    }
                  }
                },
                "right": {
                  "position": "right",
                  "attrs": {
                    "circle": {
                      "r": 4,
                      "magnet": true,
                      "stroke": "#5F95FF",
                      "strokeWidth": 1,
                      "fill": "#fff",
                      "style": {
                        "visibility": "hidden"
                      }
                    }
                  }
                },
                "bottom": {
                  "position": "bottom",
                  "attrs": {
                    "circle": {
                      "r": 4,
                      "magnet": true,
                      "stroke": "#5F95FF",
                      "strokeWidth": 1,
                      "fill": "#fff",
                      "style": {
                        "visibility": "hidden"
                      }
                    }
                  }
                },
                "left": {
                  "position": "left",
                  "attrs": {
                    "circle": {
                      "r": 4,
                      "magnet": true,
                      "stroke": "#5F95FF",
                      "strokeWidth": 1,
                      "fill": "#fff",
                      "style": {
                        "visibility": "hidden"
                      }
                    }
                  }
                }
              },
              "items": [
                {
                  "group": "top",
                  "id": "8b6284da-25af-445e-a5e0-ac682bb66f65"
                },
                {
                  "group": "right",
                  "id": "904e9e75-099b-40b8-b594-bd182b11ae83"
                },
                {
                  "group": "bottom",
                  "id": "dfed0ca2-16a6-4860-9512-6b45c3cd0773"
                },
                {
                  "group": "left",
                  "id": "758f3642-fb8d-43d4-9a3c-f2d1448301d6"
                }
              ]
            },
            "id": "9f2149c9-953a-4212-9cc5-e1d77b6e6ae5",
            "data": {
              "type": "tm.Actor",
              "name": "Authorization Provider",
              "description": "",
              "outOfScope": false,
              "reasonOutOfScope": "",
              "hasOpenThreats": true,
              "providesAuthentication": false,
              "threats": [
                {
                  "id": "d1f5e507-b87b-43dd-87df-de72c33b1cde",
                  "title": "Spoofing",
                  "status": "Open",
                  "severity": "TBD",
                  "type": "Spoofing",
                  "description": "Spoofing",
                  "mitigation": "Provide remediation for this threat or a reason if status is N/A",
                  "modelType": "STRIDE",
                  "new": false,
                  "number": 5,
                  "score": ""
                }
              ],
              "threatFrequency": {
                "spoofing": 1,
                "repudiation": 0
              }
            },
            "zIndex": 14
          },
          {
            "position": {
              "x": 1190,
              "y": 40
            },
            "size": {
              "width": 120,
              "height": 120
            },
            "attrs": {
              "text": {
                "text": "LDAP"
              },
              "body": {
                "stroke": "red",
                "strokeWidth": 2.5,
                "strokeDasharray": null
              }
            },
            "visible": true,
            "shape": "process",
            "ports": {
              "groups": {
                "top": {
                  "position": "top",
                  "attrs": {
                    "circle": {
                      "r": 4,
                      "magnet": true,
                      "stroke": "#5F95FF",
                      "strokeWidth": 1,
                      "fill": "#fff",
                      "style": {
                        "visibility": "hidden"
                      }
                    }
                  }
                },
                "right": {
                  "position": "right",
                  "attrs": {
                    "circle": {
                      "r": 4,
                      "magnet": true,
                      "stroke": "#5F95FF",
                      "strokeWidth": 1,
                      "fill": "#fff",
                      "style": {
                        "visibility": "hidden"
                      }
                    }
                  }
                },
                "bottom": {
                  "position": "bottom",
                  "attrs": {
                    "circle": {
                      "r": 4,
                      "magnet": true,
                      "stroke": "#5F95FF",
                      "strokeWidth": 1,
                      "fill": "#fff",
                      "style": {
                        "visibility": "hidden"
                      }
                    }
                  }
                },
                "left": {
                  "position": "left",
                  "attrs": {
                    "circle": {
                      "r": 4,
                      "magnet": true,
                      "stroke": "#5F95FF",
                      "strokeWidth": 1,
                      "fill": "#fff",
                      "style": {
                        "visibility": "hidden"
                      }
                    }
                  }
                }
              },
              "items": [
                {
                  "group": "top",
                  "id": "1cc156f9-c386-448d-9f3b-31d7bd57658e"
                },
                {
                  "group": "right",
                  "id": "84544158-a88b-4124-b665-95f786b45335"
                },
                {
                  "group": "bottom",
                  "id": "8e2b57c5-4c64-444c-91e0-6acb58809600"
                },
                {
                  "group": "left",
                  "id": "14be4f36-16db-455d-9924-e2f0355c5ab7"
                }
              ]
            },
            "id": "be1967c2-2a7c-4b93-b4d0-d320988b880d",
            "data": {
              "type": "tm.Process",
              "name": "LDAP",
              "description": "",
              "outOfScope": false,
              "reasonOutOfScope": "",
              "hasOpenThreats": true,
              "handlesCardPayment": false,
              "handlesGoodsOrServices": false,
              "isWebApplication": false,
              "privilegeLevel": "",
              "threats": [
                {
                  "id": "6ecafd2a-d2c7-4e71-beef-4fd1dcd8b79a",
                  "title": "Elevation of Privilege",
                  "status": "Open",
                  "severity": "TBD",
                  "type": "Elevation of privilege",
                  "description": "Elevation of Privilege",
                  "mitigation": "Provide remediation for this threat or a reason if status is N/A",
                  "modelType": "STRIDE",
                  "new": false,
                  "number": 3,
                  "score": ""
                }
              ],
              "threatFrequency": {
                "spoofing": 0,
                "tampering": 0,
                "repudiation": 0,
                "informationDisclosure": 0,
                "denialOfService": 0,
                "elevationOfPrivilege": 1
              }
            },
            "zIndex": 15
          }
        ],
        "description": "the first diagram"
      }
    ],
    "diagramTop": 2,
    "reviewer": "local",
    "threatTop": 5
  }
}